MANIFEST.in
README.md
requirements.txt
setup.cfg
setup.py
zava/__init__.py
zava/core.py
zava/plot.py
zava.egg-info/PKG-INFO
zava.egg-info/SOURCES.txt
zava.egg-info/dependency_links.txt
zava.egg-info/requires.txt
zava.egg-info/top_level.txt