Metadata-Version: 2.1
Name: zava
Version: 0.0.2
Summary: Parallel Coordinates with Grand Tour
Home-page: https://github.com/oneoffcoder/zava
Author: Jee Vang
Author-email: vangjee@gmail.com
License: UNKNOWN
Keywords: visualization parallel coordinates grand tour statistics dataframe data data mining exploratory data visualization machine learning artificial intelligence data science
Platform: UNKNOWN
Classifier: Programming Language :: Python :: 3
Classifier: License :: OSI Approved :: Apache Software License
Classifier: Operating System :: OS Independent
Classifier: Topic :: Scientific/Engineering :: Artificial Intelligence
Classifier: Intended Audience :: Developers
Classifier: Intended Audience :: Science/Research
Classifier: Development Status :: 5 - Production/Stable
